monkay/__about__.py
monkay/__init__.py
monkay/_monkay_exports.py
monkay/_monkay_extensions.py
monkay/_monkay_instance.py
monkay/_monkay_settings.py
monkay/asgi.py
monkay/base.py
monkay/cages.py
monkay/core.py
monkay/py.typed
monkay/types.py
monkay-0.5.1.dist-info/METADATA
monkay-0.5.1.dist-info/WHEEL
monkay-0.5.1.dist-info/licenses/LICENSE
monkay-0.5.1.dist-info/RECORD
